{
  "description": "Environment attestation verdicts (§27). A capability with requires_attestation=true gates grant minting on a verified Provider environment statement, bound to the Gateway's challenge nonce, unexpired, with a trusted build digest. requires_attestation=false ⇒ no attestation needed (zero friction). now is evaluation time; challenge_nonce is the Gateway-issued nonce.",
  "challenge_nonce": "nonce-abc-123",
  "now": "2026-06-13T16:00:00Z",
  "trusted_build_digests": [
    "sha256:abababababababababababababababababababababababababababababababab"
  ],
  "cases": [
    {
      "name": "not-required-no-statement",
      "requires_attestation": false,
      "statement": null,
      "expect": {
        "decision": "allow",
        "reason_code": "OK"
      }
    },
    {
      "name": "required-valid-statement",
      "requires_attestation": true,
      "statement": {
        "tier": "statement",
        "subject_role": "provider",
        "build_digest": "sha256:abababababababababababababababababababababababababababababababab",
        "nonce": "nonce-abc-123",
        "expires_at": "2026-06-13T16:30:00Z"
      },
      "expect": {
        "decision": "allow",
        "reason_code": "OK"
      }
    },
    {
      "name": "required-but-missing",
      "requires_attestation": true,
      "statement": null,
      "expect": {
        "decision": "deny",
        "reason_code": "ATTESTATION_REQUIRED"
      }
    },
    {
      "name": "required-wrong-nonce",
      "requires_attestation": true,
      "statement": {
        "tier": "statement",
        "subject_role": "provider",
        "build_digest": "sha256:abababababababababababababababababababababababababababababababab",
        "nonce": "stale-nonce",
        "expires_at": "2026-06-13T16:30:00Z"
      },
      "expect": {
        "decision": "deny",
        "reason_code": "ATTESTATION_INVALID"
      }
    },
    {
      "name": "required-untrusted-build",
      "requires_attestation": true,
      "statement": {
        "tier": "statement",
        "subject_role": "provider",
        "build_digest": "sha256:cdcdcdcdcdcdcdcdcdcdcdcdcdcdcdcdcdcdcdcdcdcdcdcdcdcdcdcdcdcdcdcd",
        "nonce": "nonce-abc-123",
        "expires_at": "2026-06-13T16:30:00Z"
      },
      "expect": {
        "decision": "deny",
        "reason_code": "ATTESTATION_INVALID"
      }
    },
    {
      "name": "required-expired",
      "requires_attestation": true,
      "statement": {
        "tier": "statement",
        "subject_role": "provider",
        "build_digest": "sha256:abababababababababababababababababababababababababababababababab",
        "nonce": "nonce-abc-123",
        "expires_at": "2026-06-13T15:50:00Z"
      },
      "expect": {
        "decision": "deny",
        "reason_code": "ATTESTATION_INVALID"
      }
    }
  ]
}
